{
    "mobileBottomRow": 32.800000000000004,
    "widgetName": "Text7Copy1",
    "displayName": "Text",
    "iconSVG": "/static/media/icon.97c59b523e6f70ba6f40a10fc2c7c5b5.svg",
    "searchTags": [
        "typography",
        "paragraph",
        "label"
    ],
    "topRow": 10.4,
    "bottomRow": 14.4,
    "parentRowSpace": 10,
    "type": "TEXT_WIDGET",
    "hideCard": false,
    "mobileRightColumn": 64,
    "animateLoading": true,
    "overflow": "NONE",
    "fontFamily": "{{appsmith.theme.fontFamily.appFont}}",
    "parentColumnSpace": 10.40625,
    "dynamicTriggerPathList": [],
    "leftColumn": 0,
    "dynamicBindingPathList": [{"key": "fontFamily"}],
    "shouldTruncate": false,
    "truncateButtonColor": "{{appsmith.theme.colors.primaryColor}}",
    "text": "Customer Address",
    "key": "lqc0eevjrg",
    "flexVerticalAlignment": "end",
    "isDeprecated": false,
    "rightColumn": 32,
    "textAlign": "LEFT",
    "dynamicHeight": "AUTO_HEIGHT",
    "widgetId": "1g1lbnuuzq",
    "minWidth": 450,
    "isVisible": true,
    "fontStyle": "BOLD",
    "textColor": "#231F20",
    "version": 1,
    "parentId": "u2cdf1egsd",
    "renderMode": "CANVAS",
    "isLoading": false,
    "mobileTopRow": 28.800000000000004,
    "responsiveBehavior": "fill",
    "borderRadius": "{{appsmith.theme.borderRadius.appBorderRadius}}",
    "mobileLeftColumn": 0,
    "maxDynamicHeight": 9000,
    "fontSize": "1rem",
    "alignment": "start",
    "minDynamicHeight": 4
}